pyfb_normalization/__init__.py
pyfb_normalization/admin.py
pyfb_normalization/api.py
pyfb_normalization/apps.py
pyfb_normalization/forms.py
pyfb_normalization/models.py
pyfb_normalization/serializers.py
pyfb_normalization/sql_config.py
pyfb_normalization/urls.py
pyfb_normalization/views.py
pyfb_normalization/migrations/0001_initial.py
pyfb_normalization/migrations/0002_auto_20190130_1726.py
pyfb_normalization/migrations/__init__.py
pyfb_normalization/static/css/pyfb_normalization.css
pyfb_normalization/static/js/pyfb_normalization.js
pyfb_normalization/templates/base.html
pyfb_normalization/templates/pyfb_normalization/callmappingrule_detail.html
pyfb_normalization/templates/pyfb_normalization/callmappingrule_form.html
pyfb_normalization/templates/pyfb_normalization/callmappingrule_list.html
pyfb_normalization/templates/pyfb_normalization/normalizationgrp_detail.html
pyfb_normalization/templates/pyfb_normalization/normalizationgrp_form.html
pyfb_normalization/templates/pyfb_normalization/normalizationgrp_list.html
pyfb_normalization/templates/pyfb_normalization/normalizationrule_detail.html
pyfb_normalization/templates/pyfb_normalization/normalizationrule_form.html
pyfb_normalization/templates/pyfb_normalization/normalizationrule_list.html
pyfb_normalization/templates/pyfb_normalization/normalizationrulegrp_detail.html
pyfb_normalization/templates/pyfb_normalization/normalizationrulegrp_form.html
pyfb_normalization/templates/pyfb_normalization/normalizationrulegrp_list.html
pyfb_normalization-1.0.2.dist-info/DESCRIPTION.rst
pyfb_normalization-1.0.2.dist-info/METADATA
pyfb_normalization-1.0.2.dist-info/RECORD
pyfb_normalization-1.0.2.dist-info/WHEEL
pyfb_normalization-1.0.2.dist-info/metadata.json
pyfb_normalization-1.0.2.dist-info/top_level.txt
